plugp100/__init__.py
plugp100/example.py
plugp100/api/__init__.py
plugp100/api/base_tapo_device.py
plugp100/api/ledstrip_device.py
plugp100/api/light_device.py
plugp100/api/light_effect.py
plugp100/api/light_effect_preset.py
plugp100/api/plug_device.py
plugp100/api/power_strip_device.py
plugp100/api/tapo_client.py
plugp100/api/hub/__init__.py
plugp100/api/hub/hub_child_device.py
plugp100/api/hub/hub_device.py
plugp100/api/hub/hub_device_tracker.py
plugp100/api/hub/ke100_device.py
plugp100/api/hub/s200b_device.py
plugp100/api/hub/switch_child_device.py
plugp100/api/hub/t100_device.py
plugp100/api/hub/t110_device.py
plugp100/api/hub/t31x_device.py
plugp100/api/hub/water_leak_device.py
plugp100/common/__init__.py
plugp100/common/credentials.py
plugp100/common/poll_tracker.py
plugp100/common/state_tracker.py
plugp100/common/functional/__init__.py
plugp100/common/functional/tri.py
plugp100/common/utils/__init__.py
plugp100/common/utils/http_client.py
plugp100/common/utils/json_utils.py
plugp100/discovery/__init__.py
plugp100/discovery/arp_lookup.py
plugp100/discovery/cloud_client.py
plugp100/discovery/discovered_device.py
plugp100/discovery/tapo_discovery.py
plugp100/encryption/__init__.py
plugp100/encryption/helpers.py
plugp100/encryption/key_pair.py
plugp100/encryption/tp_link_cipher.py
plugp100/protocol/__init__.py
plugp100/protocol/klap_protocol.py
plugp100/protocol/passthrough_protocol.py
plugp100/protocol/securepassthrough_transport.py
plugp100/protocol/tapo_protocol.py
plugp100/requests/__init__.py
plugp100/requests/handshake_params.py
plugp100/requests/login_device.py
plugp100/requests/secure_passthrough_params.py
plugp100/requests/tapo_request.py
plugp100/requests/trigger_logs_params.py
plugp100/requests/internal/__init__.py
plugp100/requests/internal/snowflake_id.py
plugp100/requests/set_device_info/__init__.py
plugp100/requests/set_device_info/play_alarm_params.py
plugp100/requests/set_device_info/set_light_color_info_params.py
tapo_forky-4.0.3.dist-info/LICENSE
tapo_forky-4.0.3.dist-info/METADATA
tapo_forky-4.0.3.dist-info/WHEEL
tapo_forky-4.0.3.dist-info/top_level.txt
tapo_forky-4.0.3.dist-info/RECORD
