Metadata-Version: 2.1
Name: tapo-forky
Version: 4.0.3
Summary: Controller for TP-Link Tapo P100 and other devices
Home-page: https://github.com/miumer/tapo
Download-URL: https://github.com/miumer/tapo
Author: @miumer
Author-email: siimpoldre@gmail.com
License: GPL3
Keywords: Tapo
Classifier: Development Status :: 5 - Production/Stable
License-File: LICENSE
Requires-Dist: certifi (>=2021.5.30)
Requires-Dist: jsons (>=1.6.3)
Requires-Dist: requests (>=2.27.1)
Requires-Dist: aiohttp (>=3.8.1)
Requires-Dist: semantic-version (==2.10.0)
Requires-Dist: cryptography (>=38.0.3)
Requires-Dist: scapy (>=2.5.0)
Requires-Dist: urllib3 (<2,>=1.26.5)
